torchvision/__init__.py
torchvision/_utils.py
torchvision/_meta_registrations.py
torchvision/_internally_replaced_utils.py
torchvision/_C.pyd
torchvision/zlib.dll
torchvision/version.py
torchvision/utils.py
torchvision/libpng16.dll
torchvision/jpeg8.dll
torchvision/image.pyd
torchvision/extension.py
torchvision/tv_tensors/__init__.py
torchvision/tv_tensors/_video.py
torchvision/tv_tensors/_tv_tensor.py
torchvision/tv_tensors/_torch_function_helpers.py
torchvision/tv_tensors/_mask.py
torchvision/tv_tensors/_image.py
torchvision/tv_tensors/_dataset_wrapper.py
torchvision/tv_tensors/_bounding_boxes.py
torchvision/transforms/__init__.py
torchvision/transforms/_transforms_video.py
torchvision/transforms/_presets.py
torchvision/transforms/_functional_video.py
torchvision/transforms/_functional_tensor.py
torchvision/transforms/_functional_pil.py
torchvision/transforms/transforms.py
torchvision/transforms/functional.py
torchvision/transforms/autoaugment.py
torchvision/transforms/v2/__init__.py
torchvision/transforms/v2/_utils.py
torchvision/transforms/v2/_type_conversion.py
torchvision/transforms/v2/_transform.py
torchvision/transforms/v2/_temporal.py
torchvision/transforms/v2/_misc.py
torchvision/transforms/v2/_meta.py
torchvision/transforms/v2/_geometry.py
torchvision/transforms/v2/_deprecated.py
torchvision/transforms/v2/_container.py
torchvision/transforms/v2/_color.py
torchvision/transforms/v2/_auto_augment.py
torchvision/transforms/v2/_augment.py
torchvision/transforms/v2/functional/__init__.py
torchvision/transforms/v2/functional/_utils.py
torchvision/transforms/v2/functional/_type_conversion.py
torchvision/transforms/v2/functional/_temporal.py
torchvision/transforms/v2/functional/_misc.py
torchvision/transforms/v2/functional/_meta.py
torchvision/transforms/v2/functional/_geometry.py
torchvision/transforms/v2/functional/_deprecated.py
torchvision/transforms/v2/functional/_color.py
torchvision/transforms/v2/functional/_augment.py
torchvision/ops/__init__.py
torchvision-0.19.1.dist-info/LICENSE
torchvision-0.19.1.dist-info/METADATA
torchvision-0.19.1.dist-info/RECORD
torchvision-0.19.1.dist-info/top_level.txt
torchvision-0.19.1.dist-info/WHEEL
