Metadata-Version: 2.1
Name: torchvision
Version: 0.19.1
Summary: image and video datasets and models for torch deep learning
Home-page: https://github.com/pytorch/vision
Author: PyTorch Core Team
Author-email: soumith@pytorch.org
License: BSD
Requires-Python: >=3.8
License-File: LICENSE
Requires-Dist: numpy
Requires-Dist: torch (==2.4.1)
Requires-Dist: pillow (!=8.3.*,>=5.3.0)
Provides-Extra: gdown
Requires-Dist: gdown (>=4.7.3) ; extra == 'gdown'
Provides-Extra: scipy
Requires-Dist: scipy ; extra == 'scipy'
